gogadget/__init__.py
gogadget/__main__.py
gogadget/cli_utils.py
gogadget/command_runner.py
gogadget/config.py
gogadget/create_anki.py
gogadget/downloader.py
gogadget/frequency_analyser.py
gogadget/help_text.py
gogadget/lemmatiser.py
gogadget/lookup.py
gogadget/main.py
gogadget/transcriber.py
gogadget/translator.py
gogadget/utils.py
gogadget/video_manipulation.py
gogadget/ytdlp_cli_to_api.py
gogadget/3rd-party-licenses/anki_LICENSE.txt
gogadget/3rd-party-licenses/bootstrap_license.txt
gogadget/3rd-party-licenses/ffmpeg-LICENSE.txt
gogadget/3rd-party-licenses/license_listing_for_python_dependencies.md
gogadget/3rd-party-licenses/uv_LICENSE.txt
gogadget/3rd-party-licenses/ytdlp_LICENSE.txt
gogadget/resources/a.mp3
gogadget/resources/a.vtt
gogadget/resources/a.vtt.gg
gogadget/resources/html/template_development.html
gogadget/resources/html/template_minimised.html
gogadget/resources/html/anki/anki_card.css
gogadget/resources/html/anki/back.html
gogadget/resources/html/anki/fields.json
gogadget/resources/html/anki/front.html
gogadget/resources/html/bootstrap/css/bootstrap.min.css
gogadget/resources/html/bootstrap/css/bootstrap.min.css.map
gogadget/resources/html/bootstrap/js/bootstrap.bundle.min.js
gogadget/resources/html/bootstrap/js/bootstrap.bundle.min.js.map
gogadget/resources/html/bootstrap/js/color-modes.js
gogadget/resources/html/bootstrap/js/color-modes.min.js
gogadget/resources/html/bootstrap/js/enable-tooltips.js
gogadget/resources/html/bootstrap/js/enable-tooltips.min.js
gogadget/resources/html/bootstrap/js/playaudio.js
gogadget/resources/html/bootstrap/js/playaudio.min.js
gogadget-0.3.3.dist-info/METADATA
gogadget-0.3.3.dist-info/WHEEL
gogadget-0.3.3.dist-info/entry_points.txt
gogadget-0.3.3.dist-info/licenses/LICENSE
gogadget-0.3.3.dist-info/RECORD
