Metadata-Version: 2.4
Name: gogadget
Version: 0.3.3
Summary: gogadget is a toolkit for producing immersion and priming materials for language learning. It is capable of downloading audio and video files, automatically transcribing subtitles from videos and podcasts, and automatically producing filtered Anki decks with sentence audio / translations / screenshots / definitions.
Project-URL: homepage, https://gogadget.jfox.io/
Project-URL: repository, https://github.com/jonathanfox5/gogadget
Project-URL: documentation, https://jonathanfox5.github.io/gogadget
Project-URL: download, https://github.com/jonathanfox5/gogadget/releases
Author: Jonathan Fox
License-File: LICENSE
Keywords: anki,frequency analysis,language learning,priming,whisper,yt-dlp
Classifier: Intended Audience :: End Users/Desktop
Classifier: License :: OSI Approved :: GNU Affero General Public License v3 or later (AGPLv3+)
Classifier: Operating System :: OS Independent
Classifier: Programming Language :: Python :: 3
Classifier: Programming Language :: Python :: 3.10
Classifier: Programming Language :: Python :: 3.11
Classifier: Programming Language :: Python :: 3.12
Classifier: Topic :: Education
Classifier: Topic :: Multimedia :: Sound/Audio
Classifier: Topic :: Multimedia :: Sound/Audio :: Analysis
Classifier: Topic :: Text Processing :: Linguistic
Requires-Python: <3.13,>=3.10
Requires-Dist: argos-spacy-compatibility<1.0.0,>=0.1.0
Requires-Dist: ctranslate2==4.5.0
Requires-Dist: ffmpeg-python<1.0.0,>=0.2.0
Requires-Dist: genanki<1.0.0,>=0.13.1
Requires-Dist: lemon-tizer<1.0.0,>=0.0.7
Requires-Dist: llvmlite==0.43.0
Requires-Dist: numba==0.60.0
Requires-Dist: numpy<2
Requires-Dist: onnxruntime==1.20.1
Requires-Dist: openpyxl<4.0.0,>=3.1.5
Requires-Dist: pandas<3.0.0,>=2.2.3
Requires-Dist: pip
Requires-Dist: pyannote-audio==3.3.2
Requires-Dist: pyannote-core==5.0.0
Requires-Dist: pysubs2<2.0.0,>=1.7.3
Requires-Dist: rtoml<1.0.0,>=0.11.0
Requires-Dist: safetensors==0.4.5
Requires-Dist: spacy==3.7.5
Requires-Dist: speechbrain==1.0.2
Requires-Dist: tokenizers==0.20.3
Requires-Dist: tomlkit<1.0.0,>=0.13.2
Requires-Dist: torch==2.8.0
Requires-Dist: torchaudio==2.8.0
Requires-Dist: transformers==4.46.3
Requires-Dist: typer<1.0.0,>=0.13.1
Requires-Dist: whisperjf<1.0.0,>=0.1.0
Requires-Dist: yt-dlp>=2025.9.5
